nayose/__init__.py
nayose/address.py
nayose/data/address.ft
nayose/data/city.ft
nayose/data/first_name.ft
nayose/data/last_name.ft
nayose/data/state.ft
nayose/data/state_and_city.ft
nayose/name.py
nayose-0.1.15.dist-info/LICENSE
nayose-0.1.15.dist-info/WHEEL
nayose-0.1.15.dist-info/METADATA
nayose-0.1.15.dist-info/RECORD
