Metadata-Version: 2.1
Name: nayose
Version: 0.1.15
Summary: nayose is a Python module for data cleansing for Japanese address and is distributed under the MIT license.
Home-page: https://github.com/sonesuke/nayose
License: MIT
Author: sonesuke
Author-email: iamsonesuke@gmail.com
Requires-Python: >=3.7.10,<4.0.0
Classifier: License :: OSI Approved :: MIT License
Classifier: Programming Language :: Python :: 3
Classifier: Programming Language :: Python :: 3.8
Classifier: Programming Language :: Python :: 3.9
Requires-Dist: feather-format (>=0.4.0,<0.5.0)
Requires-Dist: pandas (>=1.0.1,<2.0.0)
Project-URL: Repository, https://github.com/sonesuke/nayose
